numpydoclint/__init__.py
numpydoclint/cli.py
numpydoclint/constants.py
numpydoclint/introspection/__init__.py
numpydoclint/introspection/filters.py
numpydoclint/introspection/introspectors.py
numpydoclint/introspection/object_infos.py
numpydoclint/utils.py
numpydoclint/validate.py
numpydoc_linter-0.3.0.dist-info/LICENSE
numpydoc_linter-0.3.0.dist-info/METADATA
numpydoc_linter-0.3.0.dist-info/WHEEL
numpydoc_linter-0.3.0.dist-info/entry_points.txt
numpydoc_linter-0.3.0.dist-info/RECORD
