Metadata-Version: 2.1
Name: numpydoc-linter
Version: 0.3.0
Summary: Numpydoclint is a linter for Numpy style docstrings.
Home-page: https://github.com/nickuzmenkov/numpydoclint
License: MIT
Keywords: docstring,linting,documentation,code quality,python,static analysis,pep257,pep8,style guide,coding standards,syntax check,code checker
Author: Nick Kuzmenkov
Author-email: nickuzmenkov@yahoo.com
Maintainer: Nick Kuzmenkov
Maintainer-email: nickuzmenkov@yahoo.com
Requires-Python: >=3.9.0,<4.0.0
Classifier: Development Status :: 3 - Alpha
Classifier: Environment :: Console
Classifier: Intended Audience :: Developers
Classifier: License :: OSI Approved :: MIT License
Classifier: Operating System :: POSIX :: Linux
Classifier: Programming Language :: Python
Classifier: Programming Language :: Python :: 3
Classifier: Programming Language :: Python :: 3.9
Classifier: Programming Language :: Python :: 3.10
Classifier: Programming Language :: Python :: 3.11
Classifier: Programming Language :: Python :: 3 :: Only
Classifier: Topic :: Documentation
Classifier: Topic :: Software Development :: Libraries :: Python Modules
Classifier: Topic :: Software Development :: Quality Assurance
Requires-Dist: click (>=8.0,<9.0)
Requires-Dist: numpydoc (>=1.5.0,<2.0.0)
Requires-Dist: toml (>=0.10.2,<0.11.0)
Project-URL: Documentation, https://nickuzmenkov.github.io/numpydoclint/
Project-URL: Repository, https://github.com/nickuzmenkov/numpydoclint
